odoo/addons/stock_move_name_from_sale_line/README.rst
odoo/addons/stock_move_name_from_sale_line/__init__.py
odoo/addons/stock_move_name_from_sale_line/__manifest__.py
odoo/addons/stock_move_name_from_sale_line/i18n/stock_move_name_from_sale_line.pot
odoo/addons/stock_move_name_from_sale_line/models/__init__.py
odoo/addons/stock_move_name_from_sale_line/models/sale_order.py
odoo/addons/stock_move_name_from_sale_line/models/stock_rule.py
odoo/addons/stock_move_name_from_sale_line/readme/CONTRIBUTORS.rst
odoo/addons/stock_move_name_from_sale_line/readme/DESCRIPTION.rst
odoo/addons/stock_move_name_from_sale_line/static/description/icon.png
odoo/addons/stock_move_name_from_sale_line/static/description/index.html
odoo/addons/stock_move_name_from_sale_line/tests/__init__.py
odoo/addons/stock_move_name_from_sale_line/tests/test_stock_move_name_from_sale_line.py
odoo_addon_stock_move_name_from_sale_line-15.0.1.0.0.1.dist-info/METADATA
odoo_addon_stock_move_name_from_sale_line-15.0.1.0.0.1.dist-info/WHEEL
odoo_addon_stock_move_name_from_sale_line-15.0.1.0.0.1.dist-info/top_level.txt
odoo_addon_stock_move_name_from_sale_line-15.0.1.0.0.1.dist-info/RECORD
