Metadata-Version: 2.1
Name: odoo-addon-stock-move-name-from-sale-line
Version: 15.0.1.0.0.1
Summary: Set stock move name from sale line name
Home-page: https://github.com/OCA/stock-logistics-workflow
Author: Tecnativa, Odoo Community Association (OCA)
Author-email: support@odoo-community.org
License: LGPL-3
Platform: UNKNOWN
Classifier: Programming Language :: Python
Classifier: Framework :: Odoo
Classifier: Framework :: Odoo :: 15.0
Classifier: License :: OSI Approved :: GNU Lesser General Public License v3 (LGPLv3)
Requires-Python: >=3.8
Requires-Dist: odoo <15.1dev,>=15.0a
